beets_extrafiles-0.0.7-py3.7-nspkg.pth
beetsplug/extrafiles.py
beets_extrafiles-0.0.7.dist-info/LICENSE
beets_extrafiles-0.0.7.dist-info/METADATA
beets_extrafiles-0.0.7.dist-info/WHEEL
beets_extrafiles-0.0.7.dist-info/namespace_packages.txt
beets_extrafiles-0.0.7.dist-info/top_level.txt
beets_extrafiles-0.0.7.dist-info/RECORD
