Metadata-Version: 2.1
Name: beets-extrafiles
Version: 0.0.7
Summary: A plugin for beets that copies additional files and directories during the import process.
Home-page: https://github.com/Holzhaus/beets-extrafiles
Author: Jan Holthuis
Author-email: holthuis.jan@gmail.com
License: MIT
Platform: UNKNOWN
Classifier: Topic :: Multimedia :: Sound/Audio
Classifier: Topic :: Multimedia :: Sound/Audio :: Players :: MP3
Classifier: License :: OSI Approved :: MIT License
Classifier: Environment :: Console
Classifier: Environment :: Web Environment
Classifier: Programming Language :: Python :: 3
Classifier: Programming Language :: Python :: 3.5
Classifier: Programming Language :: Python :: 3.6
Classifier: Programming Language :: Python :: 3.7
Requires-Dist: beets (>=1.4.7)
